LICENSE
MANIFEST.in
setup.cfg
setup.py
raxtoken_auth_openstack/__init__.py
raxtoken_auth_openstack/plugin.py
raxtoken_auth_openstack.egg-info/PKG-INFO
raxtoken_auth_openstack.egg-info/SOURCES.txt
raxtoken_auth_openstack.egg-info/dependency_links.txt
raxtoken_auth_openstack.egg-info/entry_points.txt
raxtoken_auth_openstack.egg-info/requires.txt
raxtoken_auth_openstack.egg-info/top_level.txt