Metadata-Version: 1.1
Name: raxtoken-auth-openstack
Version: 0.1.3
Summary: Rackspace Token-Based Auth Plugin for OpenStack Clients.
Home-page: https://github.com/swyytch/raxtoken-auth-openstack
Author: Russell Troxel
Author-email: russell.troxel@rackspace.com
License: Apache License, Version 2.0
Download-URL: https://github.com/swyytch/raxtoken-auth-openstack/tarball/0.1.3
Platform: UNKNOWN
Classifier: Development Status :: 5 - Production/Stable
Classifier: Environment :: Console
Classifier: Intended Audience :: Developers
Classifier: Intended Audience :: Information Technology
Classifier: License :: OSI Approved :: Apache Software License
Classifier: Operating System :: OS Independent
Classifier: Environment :: OpenStack
Classifier: Programming Language :: Python
